graphist/__init__.py
graphist/graphist.py
graphist-0.0.1.dist-info/LICENSE
graphist-0.0.1.dist-info/METADATA
graphist-0.0.1.dist-info/WHEEL
graphist-0.0.1.dist-info/top_level.txt
graphist-0.0.1.dist-info/RECORD
