Metadata-Version: 2.1
Name: graphist
Version: 0.0.1
Summary: A package that helps add graph capabilities to your program.
Author-email: Amin Ahmadi <info@amin-ahmadi.com>
Project-URL: Homepage, https://amin-ahmadi.com
Classifier: Programming Language :: Python :: 3
Classifier: License :: OSI Approved :: MIT License
Classifier: Operating System :: OS Independent
Requires-Python: >=3.8
License-File: LICENSE
